odoo/addons/component_event/README.rst
odoo/addons/component_event/__init__.py
odoo/addons/component_event/__manifest__.py
odoo/addons/component_event/core.py
odoo/addons/component_event/components/__init__.py
odoo/addons/component_event/components/event.py
odoo/addons/component_event/i18n/component_event.pot
odoo/addons/component_event/i18n/es.po
odoo/addons/component_event/i18n/fr.po
odoo/addons/component_event/i18n/zh_CN.po
odoo/addons/component_event/models/__init__.py
odoo/addons/component_event/models/base.py
odoo/addons/component_event/readme/CONTRIBUTORS.rst
odoo/addons/component_event/readme/DESCRIPTION.rst
odoo/addons/component_event/readme/HISTORY.rst
odoo/addons/component_event/readme/USAGE.rst
odoo/addons/component_event/static/description/icon.png
odoo/addons/component_event/static/description/index.html
odoo/addons/component_event/tests/__init__.py
odoo/addons/component_event/tests/test_event.py
odoo12_addon_component_event-12.0.1.1.0.dist-info/METADATA
odoo12_addon_component_event-12.0.1.1.0.dist-info/WHEEL
odoo12_addon_component_event-12.0.1.1.0.dist-info/top_level.txt
odoo12_addon_component_event-12.0.1.1.0.dist-info/RECORD
