Metadata-Version: 2.1
Name: odoo12-addon-component-event
Version: 12.0.1.1.0
Summary: Components Events
Home-page: http://odoo-connector.com
Author: Camptocamp,Odoo Community Association (OCA)
Author-email: support@odoo-community.org
License: LGPL-3
Platform: UNKNOWN
Classifier: Programming Language :: Python
Classifier: Framework :: Odoo
Classifier: License :: OSI Approved :: GNU Lesser General Public License v3 (LGPLv3)
Requires-Python: >=3.5
Requires-Dist: cachetools
Requires-Dist: odoo12-addon-component
Requires-Dist: odoo (<12.1dev,>=12.0a)
